mehdi404_m_de_toolkit/__init__.py
mehdi404_m_de_toolkit/main.py
mehdi404_m_de_toolkit/vm.py
mehdi404_m_de_toolkit-0.1.0.dist-info/METADATA
mehdi404_m_de_toolkit-0.1.0.dist-info/WHEEL
mehdi404_m_de_toolkit-0.1.0.dist-info/entry_points.txt
mehdi404_m_de_toolkit-0.1.0.dist-info/RECORD
