Metadata-Version: 2.1
Name: mehdi404-m-de-toolkit
Version: 0.1.0
Summary: 
Author: Mehdi Messaoudi
Author-email: mehdi.messaoudi@gmx.fr
Requires-Python: >=3.8,<4.0
Classifier: Programming Language :: Python :: 3
Classifier: Programming Language :: Python :: 3.8
Classifier: Programming Language :: Python :: 3.9
Classifier: Programming Language :: Python :: 3.10
Classifier: Programming Language :: Python :: 3.11
Requires-Dist: click (>=8.1.7,<9.0.0)
